README.rst
setup.cfg
setup.py
compscifirebaselite/__init__.py
compscifirebaselite/async_compatible.py
compscifirebaselite/decorators.py
compscifirebaselite/firebase.py
compscifirebaselite/firebase_token_generator.py
compscifirebaselite/jsonutil.py
compscifirebaselite/lazy.py
compscifirebaselite.egg-info/PKG-INFO
compscifirebaselite.egg-info/SOURCES.txt
compscifirebaselite.egg-info/dependency_links.txt
compscifirebaselite.egg-info/not-zip-safe
compscifirebaselite.egg-info/requires.txt
compscifirebaselite.egg-info/top_level.txt