Metadata-Version: 1.1
Name: compscifirebaselite
Version: 1.0.0
Summary: Computer Science Firebase Package which is a lite version for python-firebase
Home-page: https://github.com/MrGallen/firebase-compsci
Author: Eoin Gallen
Author-email: egallen@sainteunans.com
License: MIT
Keywords: firebase python
Platform: UNKNOWN
Classifier: Development Status :: 5 - Production/Stable
Classifier: Environment :: Console
Classifier: Intended Audience :: Developers
Classifier: License :: OSI Approved :: MIT License
Classifier: Operating System :: OS Independent
Classifier: Programming Language :: Python :: 3.9
Classifier: Programming Language :: Python :: 3.8
Classifier: Programming Language :: Python :: 3.2
Classifier: Natural Language :: English
